[
    {
        "name": "Basilisk-tongue",
        "combattech": "Daggers",
        "primeattr": "AGI",
        "threshold": 14,
        "damage": "1W6",
        "bonus": 2,
        "at": 0,
        "pa": -1,
        "range": 1,
        "weight": "0,5Stn",
        "price": 50,
        "sf": 12,
        "primeattrID": "ATTR_6",
        "combattechID": "CT_3",
        "improvised": false,
        "url": "",
        "clsrng": true,
        "armed": true,
        "templateID": "ITEMTPL_1"
    },
    {
        "name": "Dagger",
        "combattech": "Daggers",
        "primeattr": "AGI",
        "threshold": 14,
        "damage": "1W6",
        "bonus": 1,
        "at": 0,
        "pa": 0,
        "range": 1,
        "weight": "0,5Stn",
        "price": 45,
        "sf": 12,
        "primeattrID": "ATTR_6",
        "combattechID": "CT_3",
        "improvised": false,
        "url": "",
        "clsrng": true,
        "armed": true,
        "templateID": "ITEMTPL_2"
    },
    {
        "name": "Dragon tooth",
        "combattech": "Daggers",
        "primeattr": "AGI",
        "threshold": 14,
        "damage": "1W6",
        "bonus": 2,
        "at": 0,
        "pa": -1,
        "range": 1,
        "weight": "0,75Stn",
        "price": 70,
        "sf": 12,
        "primeattrID": "ATTR_6",
        "combattechID": "CT_3",
        "improvised": false,
        "url": "",
        "clsrng": true,
        "armed": true,
        "templateID": "ITEMTPL_3"
    },
    {
        "name": "--Linkhand",
        "combattech": "Daggers",
        "primeattr": "AGI",
        "threshold": 14,
        "damage": "1W6",
        "bonus": 1,
        "at": 0,
        "pa": 0,
        "range": 1,
        "weight": "0,75Stn",
        "price": 90,
        "sf": 12,
        "primeattrID": "ATTR_6",
        "combattechID": "CT_3",
        "improvised": false,
        "url": "index.php/linkhand.html",
        "clsrng": true,
        "armed": true,
        "templateID": "ITEMTPL_4"
    },
    {
        "name": "Knife",
        "combattech": "Daggers",
        "primeattr": "AGI",
        "threshold": 14,
        "damage": "1W6",
        "bonus": 1,
        "at": 0,
        "pa": -2,
        "range": 1,
        "weight": "0,25Stn",
        "price": 10,
        "sf": 12,
        "primeattrID": "ATTR_6",
        "combattechID": "CT_3",
        "improvised": false,
        "url": "",
        "clsrng": true,
        "armed": true,
        "templateID": "ITEMTPL_5"
    },
    {
        "name": "Heavy Dagger",
        "combattech": "Daggers",
        "primeattr": "AGI",
        "threshold": 14,
        "damage": "1W6",
        "bonus": 2,
        "at": 0,
        "pa": -1,
        "range": 1,
        "weight": "0,75Stn",
        "price": 60,
        "sf": 12,
        "primeattrID": "ATTR_6",
        "combattechID": "CT_3",
        "improvised": false,
        "url": "",
        "clsrng": true,
        "armed": true,
        "templateID": "ITEMTPL_6"
    },
    {
        "name": "Waqqif",
        "combattech": "Daggers",
        "primeattr": "AGI",
        "threshold": 14,
        "damage": "1W6",
        "bonus": 2,
        "at": 0,
        "pa": -1,
        "range": 1,
        "weight": "0,5Stn",
        "price": 60,
        "sf": 12,
        "primeattrID": "ATTR_6",
        "combattechID": "CT_3",
        "improvised": false,
        "url": "",
        "clsrng": true,
        "armed": true,
        "templateID": "ITEMTPL_7"
    },
    {
        "name": "Foil",
        "combattech": "Fencing",
        "primeattr": "AGI",
        "threshold": 14,
        "damage": "1W6",
        "bonus": 2,
        "at": 1,
        "pa": 0,
        "range": 2,
        "weight": "0,5Stn",
        "price": 300,
        "sf": 12,
        "primeattrID": "ATTR_6",
        "combattechID": "CT_4",
        "improvised": false,
        "url": "",
        "clsrng": true,
        "armed": true,
        "templateID": "ITEMTPL_8"
    },
    {
        "name": "Rapier",
        "combattech": "Fencing",
        "primeattr": "AGI",
        "threshold": 15,
        "damage": "1W6",
        "bonus": 3,
        "at": 1,
        "pa": 0,
        "range": 2,
        "weight": "1Stn",
        "price": 200,
        "sf": 12,
        "primeattrID": "ATTR_6",
        "combattechID": "CT_4",
        "improvised": false,
        "url": "",
        "clsrng": true,
        "armed": true,
        "templateID": "ITEMTPL_9"
    },
    {
        "name": "Wolf-knife",
        "combattech": "Fencing",
        "primeattr": "AGI",
        "threshold": 15,
        "damage": "1W6",
        "bonus": 3,
        "at": 1,
        "pa": 1,
        "range": 2,
        "weight": "0,5Stn",
        "price": 300,
        "sf": 12,
        "primeattrID": "ATTR_6",
        "combattechID": "CT_4",
        "improvised": false,
        "url": "",
        "clsrng": true,
        "armed": true,
        "templateID": "ITEMTPL_10"
    },
    {
        "name": "Cudgel, Brabak",
        "combattech": "Impact Weapons",
        "primeattr": "STR",
        "threshold": 14,
        "damage": "1W6",
        "bonus": 5,
        "at": -1,
        "pa": -2,
        "range": 2,
        "weight": "2Stn",
        "price": 170,
        "sf": 12,
        "primeattrID": "ATTR_8",
        "combattechID": "CT_5",
        "improvised": false,
        "url": "",
        "clsrng": true,
        "armed": true,
        "templateID": "ITEMTPL_11"
    },
    {
        "name": "Cudgel",
        "combattech": "Impact Weapons",
        "primeattr": "STR",
        "threshold": 14,
        "damage": "1W6",
        "bonus": 3,
        "at": 0,
        "pa": -1,
        "range": 2,
        "weight": "0,75Stn",
        "price": 3,
        "sf": 12,
        "primeattrID": "ATTR_8",
        "combattechID": "CT_5",
        "improvised": false,
        "url": "",
        "clsrng": true,
        "armed": true,
        "templateID": "ITEMTPL_12"
    },
    {
        "name": "Club",
        "combattech": "Impact Weapons",
        "primeattr": "STR",
        "threshold": 14,
        "damage": "1W6",
        "bonus": 2,
        "at": 0,
        "pa": -2,
        "range": 2,
        "weight": "0,5Stn",
        "price": 0,
        "sf": 12,
        "primeattrID": "ATTR_8",
        "combattechID": "CT_5",
        "improvised": false,
        "url": "",
        "clsrng": true,
        "armed": true,
        "templateID": "ITEMTPL_13"
    },
    {
        "name": "Wyvern-beater",
        "combattech": "Impact Weapons",
        "primeattr": "STR",
        "threshold": 14,
        "damage": "1W6",
        "bonus": 4,
        "at": 0,
        "pa": -1,
        "range": 1,
        "weight": "1Stn",
        "price": 90,
        "sf": 12,
        "primeattrID": "ATTR_8",
        "combattechID": "CT_5",
        "improvised": false,
        "url": "",
        "clsrng": true,
        "armed": true,
        "templateID": "ITEMTPL_14"
    },
    {
        "name": "Mage’s staff, short",
        "combattech": "Impact Weapons",
        "primeattr": "STR",
        "threshold": 14,
        "damage": "1W6",
        "bonus": 1,
        "at": 0,
        "pa": -1,
        "range": 1,
        "weight": "0,75Stn",
        "price": 40,
        "sf": 12,
        "primeattrID": "ATTR_8",
        "combattechID": "CT_5",
        "improvised": false,
        "url": "",
        "clsrng": true,
        "armed": true,
        "templateID": "ITEMTPL_15"
    },
    {
        "name": "Mage’s staff, medium",
        "combattech": "Impact Weapons",
        "primeattr": "STR",
        "threshold": 14,
        "damage": "1W6",
        "bonus": 2,
        "at": 0,
        "pa": -1,
        "range": 2,
        "weight": "0,75Stn",
        "price": 60,
        "sf": 12,
        "primeattrID": "ATTR_8",
        "combattechID": "CT_5",
        "improvised": false,
        "url": "",
        "clsrng": true,
        "armed": true,
        "templateID": "ITEMTPL_16"
    },
    {
        "name": "Molokdeshnaja",
        "combattech": "Impact Weapons",
        "primeattr": "STR",
        "threshold": 14,
        "damage": "1W6",
        "bonus": 4,
        "at": 0,
        "pa": -1,
        "range": 2,
        "weight": "1,25Stn",
        "price": 95,
        "sf": 12,
        "primeattrID": "ATTR_8",
        "combattechID": "CT_5",
        "improvised": false,
        "url": "",
        "clsrng": true,
        "armed": true,
        "templateID": "ITEMTPL_17"
    },
    {
        "name": "Orc-nose",
        "combattech": "Impact Weapons",
        "primeattr": "STR",
        "threshold": 14,
        "damage": "1W6",
        "bonus": 5,
        "at": -1,
        "pa": -2,
        "range": 2,
        "weight": "1,75Stn",
        "price": 120,
        "sf": 12,
        "primeattrID": "ATTR_8",
        "combattechID": "CT_5",
        "improvised": false,
        "url": "",
        "clsrng": true,
        "armed": true,
        "templateID": "ITEMTPL_18"
    },
    {
        "name": "Raven’s beak",
        "combattech": "Impact Weapons",
        "primeattr": "STR",
        "threshold": 14,
        "damage": "1W6",
        "bonus": 4,
        "at": 0,
        "pa": -1,
        "range": 2,
        "weight": "1,5Stn",
        "price": 105,
        "sf": 12,
        "primeattrID": "ATTR_8",
        "combattechID": "CT_5",
        "improvised": false,
        "url": "",
        "clsrng": true,
        "armed": true,
        "templateID": "ITEMTPL_796"
    },
    {
        "name": "Sun-scepter",
        "combattech": "Impact Weapons",
        "primeattr": "STR",
        "threshold": 14,
        "damage": "1W6",
        "bonus": 3,
        "at": 0,
        "pa": -1,
        "range": 2,
        "weight": "1,25Stn",
        "price": 250,
        "sf": 12,
        "primeattrID": "ATTR_8",
        "combattechID": "CT_5",
        "improvised": false,
        "url": "",
        "clsrng": true,
        "armed": true,
        "templateID": "ITEMTPL_20"
    },
    {
        "name": "Battleaxe",
        "combattech": "Impact Weapons",
        "primeattr": "STR",
        "threshold": 14,
        "damage": "1W6",
        "bonus": 4,
        "at": 0,
        "pa": -1,
        "range": 2,
        "weight": "1,5Stn",
        "price": 105,
        "sf": 12,
        "primeattrID": "ATTR_8",
        "combattechID": "CT_5",
        "improvised": false,
        "url": "",
        "clsrng": true,
        "armed": true,
        "templateID": "ITEMTPL_21"
    },
    {
        "name": "Mace",
        "combattech": "Impact Weapons",
        "primeattr": "STR",
        "threshold": 14,
        "damage": "1W6",
        "bonus": 4,
        "at": 0,
        "pa": -1,
        "range": 2,
        "weight": "1,5Stn",
        "price": 105,
        "sf": 12,
        "primeattrID": "ATTR_8",
        "combattechID": "CT_5",
        "improvised": false,
        "url": "",
        "clsrng": true,
        "armed": true,
        "templateID": "ITEMTPL_22"
    },
    {
        "name": "Flail",
        "combattech": "Kettenwaffen",
        "primeattr": "STR",
        "threshold": 14,
        "damage": "1W6",
        "bonus": 5,
        "at": 0,
        "range": 2,
        "weight": "1,5Stn",
        "price": 110,
        "sf": 12,
        "primeattrID": "ATTR_8",
        "combattechID": "CT_6",
        "improvised": false,
        "url": "",
        "clsrng": true,
        "armed": true,
        "templateID": "ITEMTPL_23"
    },
    {
        "name": "War lance",
        "combattech": "Lanzen",
        "damage": "2W6",
        "bonus": 6,
        "weight": "3,75Stn",
        "price": 100,
        "sf": 12,
        "primeattrID": "ATTR_8",
        "combattechID": "CT_7",
        "improvised": false,
        "url": "",
        "clsrng": true,
        "armed": true,
        "templateID": "ITEMTPL_24"
    },
    {
        "name": "Brass knuckles",
        "combattech": "Brawling",
        "primeattr": "AGI/STR",
        "threshold": 15,
        "damage": "1W6",
        "bonus": 1,
        "at": 0,
        "pa": 0,
        "range": 1,
        "weight": "0,25Stn",
        "price": 25,
        "sf": 12,
        "primeattrID": "ATTR_6/ATTR_8",
        "combattechID": "CT_9",
        "improvised": false,
        "url": "",
        "clsrng": true,
        "armed": true,
        "templateID": "ITEMTPL_25"
    },
    {
        "name": "Umnarmed",
        "combattech": "Brawling",
        "primeattr": "AGI/STR",
        "threshold": 14,
        "damage": "1W6",
        "bonus": 0,
        "at": 0,
        "pa": 0,
        "range": 1,
        "weight": "-",
        "price": 0,
        "sf": 12,
        "primeattrID": "ATTR_6/ATTR_8",
        "combattechID": "CT_9",
        "improvised": false,
        "url": "",
        "clsrng": true,
        "armed": false,
        "templateID": "WEAPONLESS"
    },
    {
        "name": "Wooden shield",
        "combattech": "Shields",
        "primeattr": "STR",
        "threshold": 16,
        "damage": "1W6",
        "at": -4,
        "pa": 1,
        "range": 1,
        "weight": "3,5Stn",
        "price": 50,
        "sf": 12,
        "primeattrID": "ATTR_8",
        "combattechID": "CT_10",
        "improvised": false,
        "url": "",
        "clsrng": true,
        "armed": true,
        "templateID": "ITEMTPL_26"
    },
    {
        "name": "Leather shield",
        "combattech": "Shields",
        "primeattr": "STR",
        "threshold": 16,
        "damage": "1W6",
        "at": -4,
        "pa": 1,
        "range": 1,
        "weight": "2Stn",
        "price": 30,
        "sf": 12,
        "primeattrID": "ATTR_8",
        "combattechID": "CT_10",
        "improvised": false,
        "url": "",
        "clsrng": true,
        "armed": true,
        "templateID": "ITEMTPL_27"
    },
    {
        "name": "Thorwaler shield",
        "combattech": "Shields",
        "primeattr": "STR",
        "threshold": 16,
        "damage": "1W6",
        "bonus": 1,
        "at": -5,
        "pa": 2,
        "range": 1,
        "weight": "4,5Stn",
        "price": 70,
        "sf": 12,
        "primeattrID": "ATTR_8",
        "combattechID": "CT_10",
        "improvised": false,
        "url": "",
        "clsrng": true,
        "armed": true,
        "templateID": "ITEMTPL_28"
    },
    {
        "name": "Great shield",
        "combattech": "Shields",
        "primeattr": "STR",
        "threshold": 16,
        "damage": "1W6",
        "bonus": 1,
        "at": -6,
        "pa": 3,
        "range": 1,
        "weight": "6Stn",
        "price": 100,
        "sf": 12,
        "primeattrID": "ATTR_8",
        "combattechID": "CT_10",
        "improvised": false,
        "url": "",
        "clsrng": true,
        "armed": true,
        "templateID": "ITEMTPL_29"
    },
    {
        "name": "Barbarian sword",
        "combattech": "Swords",
        "primeattr": "AGI/STR",
        "threshold": 15,
        "damage": "1W6",
        "bonus": 5,
        "at": -1,
        "pa": -1,
        "range": 2,
        "weight": "1,5Stn",
        "price": 140,
        "sf": 12,
        "primeattrID": "ATTR_6/ATTR_8",
        "combattechID": "CT_12",
        "improvised": false,
        "url": "",
        "clsrng": true,
        "armed": true,
        "templateID": "ITEMTPL_30"
    },
    {
        "name": "Cutlass",
        "combattech": "Swords",
        "primeattr": "AGI/STR",
        "threshold": 15,
        "damage": "1W6",
        "bonus": 3,
        "at": 0,
        "pa": -1,
        "range": 2,
        "weight": "0,75Stn",
        "price": 120,
        "sf": 12,
        "primeattrID": "ATTR_6/ATTR_8",
        "combattechID": "CT_12",
        "improvised": false,
        "url": "",
        "clsrng": true,
        "armed": true,
        "templateID": "ITEMTPL_31"
    },
    {
        "name": "--Flammenschwert",
        "combattech": "Swords",
        "primeattr": "AGI/STR",
        "threshold": 15,
        "damage": "1W6",
        "bonus": 7,
        "at": 0,
        "pa": 0,
        "range": 2,
        "weight": "1AsP/KR",
        "price": 0,
        "sf": 12,
        "primeattrID": "ATTR_6/ATTR_8",
        "combattechID": "CT_12",
        "improvised": false,
        "url": "",
        "clsrng": true,
        "armed": true
    },
    {
        "name": "--Flammenschwert(fern)",
        "combattech": "Swords",
        "primeattr": "AGI/STR",
        "threshold": 99,
        "damage": "1W6",
        "bonus": 7,
        "at": 0,
        "range": 3,
        "weight": "2AsP/KR",
        "price": 0,
        "sf": 12,
        "primeattrID": "ATTR_6/ATTR_8",
        "combattechID": "CT_12",
        "improvised": false,
        "url": "",
        "clsrng": true,
        "armed": true
    },
    {
        "name": "Slasher",
        "combattech": "Swords",
        "primeattr": "AGI/STR",
        "threshold": 15,
        "damage": "1W6",
        "bonus": 3,
        "at": 0,
        "pa": -1,
        "range": 2,
        "weight": "0,75Stn",
        "price": 100,
        "sf": 12,
        "primeattrID": "ATTR_6/ATTR_8",
        "combattechID": "CT_12",
        "improvised": false,
        "url": "",
        "clsrng": true,
        "armed": true,
        "templateID": "ITEMTPL_32"
    },
    {
        "name": "Khunchomer",
        "combattech": "Swords",
        "primeattr": "AGI/STR",
        "threshold": 15,
        "damage": "1W6",
        "bonus": 4,
        "at": 0,
        "pa": 0,
        "range": 2,
        "weight": "1,25Stn",
        "price": 210,
        "sf": 12,
        "primeattrID": "ATTR_6/ATTR_8",
        "combattechID": "CT_12",
        "improvised": false,
        "url": "",
        "clsrng": true,
        "armed": true,
        "templateID": "ITEMTPL_33"
    },
    {
        "name": "Short sword",
        "combattech": "Swords",
        "primeattr": "AGI/STR",
        "threshold": 15,
        "damage": "1W6",
        "bonus": 2,
        "at": 0,
        "pa": 0,
        "range": 1,
        "weight": "0,75Stn",
        "price": 140,
        "sf": 12,
        "primeattrID": "ATTR_6/ATTR_8",
        "combattechID": "CT_12",
        "improvised": false,
        "url": "",
        "clsrng": true,
        "armed": true,
        "templateID": "ITEMTPL_34"
    },
    {
        "name": "Long sword",
        "combattech": "Swords",
        "primeattr": "AGI/STR",
        "threshold": 15,
        "damage": "1W6",
        "bonus": 4,
        "at": 0,
        "pa": 0,
        "range": 2,
        "weight": "1Stn",
        "price": 200,
        "sf": 12,
        "primeattrID": "ATTR_6/ATTR_8",
        "combattechID": "CT_12",
        "improvised": false,
        "url": "",
        "clsrng": true,
        "armed": true,
        "templateID": "ITEMTPL_35"
    },
    {
        "name": "Seal-killer",
        "combattech": "Swords",
        "primeattr": "AGI/STR",
        "threshold": 15,
        "damage": "1W6",
        "bonus": 4,
        "at": 0,
        "pa": 0,
        "range": 2,
        "weight": "1Stn",
        "price": 200,
        "sf": 12,
        "primeattrID": "ATTR_6/ATTR_8",
        "combattechID": "CT_12",
        "improvised": false,
        "url": "",
        "clsrng": true,
        "armed": true,
        "templateID": "ITEMTPL_36"
    },
    {
        "name": "Saber",
        "combattech": "Swords",
        "primeattr": "AGI/STR",
        "threshold": 15,
        "damage": "1W6",
        "bonus": 3,
        "at": 0,
        "pa": 0,
        "range": 2,
        "weight": "0,75Stn",
        "price": 180,
        "sf": 12,
        "primeattrID": "ATTR_6/ATTR_8",
        "combattechID": "CT_12",
        "improvised": false,
        "url": "",
        "clsrng": true,
        "armed": true,
        "templateID": "ITEMTPL_37"
    },
    {
        "name": "Slave-death",
        "combattech": "Swords",
        "primeattr": "AGI/STR",
        "threshold": 15,
        "damage": "1W6",
        "bonus": 4,
        "at": 0,
        "pa": 0,
        "range": 2,
        "weight": "1,25Stn",
        "price": 210,
        "sf": 12,
        "primeattrID": "ATTR_6/ATTR_8",
        "combattechID": "CT_12",
        "improvised": false,
        "url": "",
        "clsrng": true,
        "armed": true,
        "templateID": "ITEMTPL_38"
    },
    {
        "name": "Trident",
        "combattech": "Polearms",
        "primeattr": "AGI/STR",
        "threshold": 15,
        "damage": "1W6",
        "bonus": 4,
        "at": 0,
        "pa": 0,
        "range": 3,
        "weight": "2Stn",
        "price": 80,
        "sf": 12,
        "primeattrID": "ATTR_6/ATTR_8",
        "combattechID": "CT_13",
        "improvised": false,
        "url": "",
        "clsrng": true,
        "armed": true,
        "templateID": "ITEMTPL_148"
    },
    {
        "name": "Dshadra",
        "combattech": "Polearms",
        "primeattr": "AGI/STR",
        "threshold": 15,
        "damage": "1W6",
        "bonus": 5,
        "at": 0,
        "pa": -1,
        "range": 3,
        "weight": "2Stn",
        "price": 60,
        "sf": 12,
        "primeattrID": "ATTR_6/ATTR_8",
        "combattechID": "CT_13",
        "improvised": false,
        "url": "",
        "clsrng": true,
        "armed": true,
        "templateID": "ITEMTPL_40"
    },
    {
        "name": "Halberd",
        "combattech": "Polearms",
        "primeattr": "AGI/STR",
        "threshold": 15,
        "damage": "1W6",
        "bonus": 6,
        "at": 0,
        "pa": -2,
        "range": 3,
        "weight": "2,5Stn",
        "price": 160,
        "sf": 12,
        "primeattrID": "ATTR_6/ATTR_8",
        "combattechID": "CT_13",
        "improvised": false,
        "url": "",
        "clsrng": true,
        "armed": true,
        "templateID": "ITEMTPL_41"
    },
    {
        "name": "Wooden spear",
        "combattech": "Polearms",
        "primeattr": "AGI/STR",
        "threshold": 15,
        "damage": "1W6",
        "bonus": 2,
        "at": 0,
        "pa": 0,
        "range": 3,
        "weight": "1Stn",
        "price": 1,
        "sf": 12,
        "primeattrID": "ATTR_6/ATTR_8",
        "combattechID": "CT_13",
        "improvised": false,
        "url": "",
        "clsrng": true,
        "armed": true,
        "templateID": "ITEMTPL_42"
    },
    {
        "name": "Quarterstaff",
        "combattech": "Polearms",
        "primeattr": "AGI/STR",
        "threshold": 15,
        "damage": "1W6",
        "bonus": 2,
        "at": 0,
        "pa": 2,
        "range": 3,
        "weight": "1Stn",
        "price": 40,
        "sf": 12,
        "primeattrID": "ATTR_6/ATTR_8",
        "combattechID": "CT_13",
        "improvised": false,
        "url": "",
        "clsrng": true,
        "armed": true,
        "templateID": "ITEMTPL_43"
    },
    {
        "name": "Mage’s staff, long",
        "combattech": "Polearms",
        "primeattr": "AGI/STR",
        "threshold": 16,
        "damage": "1W6",
        "bonus": 2,
        "at": -1,
        "pa": 2,
        "range": 3,
        "weight": "0,75Stn",
        "price": 80,
        "sf": 12,
        "primeattrID": "ATTR_6/ATTR_8",
        "combattechID": "CT_13",
        "improvised": false,
        "url": "",
        "clsrng": true,
        "armed": true,
        "templateID": "ITEMTPL_44"
    },
    {
        "name": "Spear",
        "combattech": "Polearms",
        "primeattr": "AGI/STR",
        "threshold": 15,
        "damage": "1W6",
        "bonus": 4,
        "at": 0,
        "pa": 0,
        "range": 3,
        "weight": "2Stn",
        "price": 45,
        "sf": 12,
        "primeattrID": "ATTR_6/ATTR_8",
        "combattechID": "CT_13",
        "improvised": false,
        "url": "",
        "clsrng": true,
        "armed": true,
        "templateID": "ITEMTPL_45"
    },
    {
        "name": "Two-lilies",
        "combattech": "Polearms",
        "primeattr": "AGI/STR",
        "threshold": 15,
        "damage": "1W6",
        "bonus": 4,
        "at": 0,
        "pa": 2,
        "range": 2,
        "weight": "2Stn",
        "price": 200,
        "sf": 12,
        "primeattrID": "ATTR_6/ATTR_8",
        "combattechID": "CT_13",
        "improvised": false,
        "url": "",
        "clsrng": true,
        "armed": true,
        "templateID": "ITEMTPL_46"
    },
    {
        "name": "Bastard sword",
        "combattech": "Two-Handed Swords",
        "primeattr": "STR",
        "threshold": 14,
        "damage": "1W6",
        "bonus": 6,
        "at": 0,
        "pa": 0,
        "range": 2,
        "weight": "2Stn",
        "price": 320,
        "sf": 12,
        "primeattrID": "ATTR_8",
        "combattechID": "CT_16",
        "improvised": false,
        "url": "",
        "clsrng": true,
        "armed": true,
        "templateID": "ITEMTPL_47"
    },
    {
        "name": "Double-khunchomer",
        "combattech": "Two-Handed Swords",
        "primeattr": "STR",
        "threshold": 14,
        "damage": "2W6",
        "bonus": 3,
        "at": 0,
        "pa": -2,
        "range": 2,
        "weight": "2Stn",
        "price": 320,
        "sf": 12,
        "primeattrID": "ATTR_8",
        "combattechID": "CT_16",
        "improvised": false,
        "url": "",
        "clsrng": true,
        "armed": true,
        "templateID": "ITEMTPL_48"
    },
    {
        "name": "Great slave-death",
        "combattech": "Two-Handed Swords",
        "primeattr": "STR",
        "threshold": 14,
        "damage": "2W6",
        "bonus": 3,
        "at": 0,
        "pa": -2,
        "range": 2,
        "weight": "2Stn",
        "price": 320,
        "sf": 12,
        "primeattrID": "ATTR_8",
        "combattechID": "CT_16",
        "improvised": false,
        "url": "",
        "clsrng": true,
        "armed": true,
        "templateID": "ITEMTPL_49"
    },
    {
        "name": "Rondra’s Crest",
        "combattech": "Two-Handed Swords",
        "primeattr": "STR",
        "threshold": 14,
        "damage": "2W6",
        "bonus": 2,
        "at": 0,
        "pa": -1,
        "range": 2,
        "weight": "2Stn",
        "price": 340,
        "sf": 12,
        "primeattrID": "ATTR_8",
        "combattechID": "CT_16",
        "improvised": false,
        "url": "",
        "clsrng": true,
        "armed": true,
        "templateID": "ITEMTPL_50"
    },
    {
        "name": "Tuzak knife",
        "combattech": "Two-Handed Swords",
        "primeattr": "STR",
        "threshold": 14,
        "damage": "1W6",
        "bonus": 6,
        "at": 0,
        "pa": 0,
        "range": 2,
        "weight": "1,75Stn",
        "price": 360,
        "sf": 12,
        "primeattrID": "ATTR_8",
        "combattechID": "CT_16",
        "improvised": false,
        "url": "",
        "clsrng": true,
        "armed": true,
        "templateID": "ITEMTPL_51"
    },
    {
        "name": "Great sword",
        "combattech": "Two-Handed Swords",
        "primeattr": "STR",
        "threshold": 14,
        "damage": "2W6",
        "bonus": 4,
        "at": 0,
        "pa": -3,
        "range": 2,
        "weight": "2,5Stn",
        "price": 360,
        "sf": 12,
        "primeattrID": "ATTR_8",
        "combattechID": "CT_16",
        "improvised": false,
        "url": "",
        "clsrng": true,
        "armed": true,
        "templateID": "ITEMTPL_52"
    },
    {
        "name": "Barbarenstreitaxt",
        "combattech": "Two-Handed Impact Weapons",
        "primeattr": "STR",
        "threshold": 13,
        "damage": "2W6",
        "bonus": 4,
        "at": 0,
        "pa": -4,
        "range": 2,
        "weight": "3,5Stn",
        "price": 175,
        "sf": 12,
        "primeattrID": "ATTR_8",
        "combattechID": "CT_15",
        "improvised": false,
        "url": "",
        "clsrng": true,
        "armed": true,
        "templateID": "ITEMTPL_53"
    },
    {
        "name": "Rock-cleaver",
        "combattech": "Two-Handed Impact Weapons",
        "primeattr": "STR",
        "threshold": 13,
        "damage": "2W6",
        "bonus": 2,
        "at": 0,
        "pa": -2,
        "range": 2,
        "weight": "3Stn",
        "price": 200,
        "sf": 12,
        "primeattrID": "ATTR_8",
        "combattechID": "CT_15",
        "improvised": false,
        "url": "",
        "clsrng": true,
        "armed": true,
        "templateID": "ITEMTPL_54"
    },
    {
        "name": "Warhammer",
        "combattech": "Two-Handed Impact Weapons",
        "primeattr": "STR",
        "threshold": 13,
        "damage": "2W6",
        "bonus": 3,
        "at": 0,
        "pa": -3,
        "range": 2,
        "weight": "3Stn",
        "price": 170,
        "sf": 12,
        "primeattrID": "ATTR_8",
        "combattechID": "CT_15",
        "improvised": false,
        "url": "",
        "clsrng": true,
        "armed": true,
        "templateID": "ITEMTPL_55"
    },
    {
        "name": "Dwarf cudgel",
        "combattech": "Two-Handed Impact Weapons",
        "primeattr": "STR",
        "threshold": 13,
        "damage": "1W6",
        "bonus": 6,
        "at": 0,
        "pa": -1,
        "range": 2,
        "weight": "3Stn",
        "price": 100,
        "sf": 12,
        "primeattrID": "ATTR_8",
        "combattechID": "CT_15",
        "improvised": false,
        "url": "",
        "clsrng": true,
        "armed": true,
        "templateID": "ITEMTPL_56"
    },
    {
        "name": "Druid Dagger",
        "combattech": "Daggers",
        "primeattr": "AGI",
        "threshold": 15,
        "damage": "1W6",
        "bonus": 1,
        "at": -1,
        "pa": 0,
        "range": 1,
        "weight": "0,5Stn",
        "price": 60,
        "sf": 12,
        "primeattrID": "ATTR_6",
        "combattechID": "CT_3",
        "improvised": false,
        "url": "",
        "clsrng": true,
        "armed": true,
        "templateID": "ITEMTPL_474"
    },
    {
        "name": "Boar-catcher",
        "combattech": "Daggers",
        "primeattr": "AGI",
        "threshold": 14,
        "damage": "1W6",
        "bonus": 2,
        "at": 0,
        "pa": -1,
        "range": 1,
        "weight": "1Stn",
        "price": 60,
        "sf": 12,
        "primeattrID": "ATTR_6",
        "combattechID": "CT_3",
        "improvised": false,
        "url": "",
        "clsrng": true,
        "armed": true,
        "templateID": "ITEMTPL_475"
    },
    {
        "name": "Dike Fork",
        "combattech": "Impact Weapons",
        "primeattr": "STR",
        "threshold": 15,
        "damage": "1W6",
        "bonus": 2,
        "at": -1,
        "pa": -2,
        "range": 2,
        "weight": "0,5Stn",
        "price": 30,
        "sf": 12,
        "primeattrID": "ATTR_8",
        "combattechID": "CT_5",
        "improvised": true,
        "url": "",
        "clsrng": true,
        "armed": true,
        "templateID": "ITEMTPL_476"
    },
    {
        "name": "Tournament Lance",
        "combattech": "Lanzen",
        "damage": "1W6",
        "bonus": 8,
        "weight": "3Stn",
        "price": 30,
        "sf": 12,
        "primeattrID": "ATTR_8",
        "combattechID": "CT_7",
        "improvised": false,
        "url": "",
        "clsrng": true,
        "armed": true,
        "templateID": "ITEMTPL_385"
    },
    {
        "name": "Stag-Catcher",
        "combattech": "Swords",
        "primeattr": "AGI/STR",
        "threshold": 14,
        "damage": "1W6",
        "bonus": 2,
        "at": 0,
        "pa": -1,
        "range": 1,
        "weight": "1Stn",
        "price": 100,
        "sf": 12,
        "primeattrID": "ATTR_6/ATTR_8",
        "combattechID": "CT_12",
        "improvised": false,
        "url": "",
        "clsrng": true,
        "armed": true,
        "templateID": "ITEMTPL_477"
    },
    {
        "name": "Tournament Sword",
        "combattech": "Swords",
        "primeattr": "AGI/STR",
        "threshold": 16,
        "damage": "1W6",
        "bonus": 1,
        "at": 0,
        "pa": 0,
        "range": 2,
        "weight": "0,5Stn",
        "price": 20,
        "sf": 12,
        "primeattrID": "ATTR_6/ATTR_8",
        "combattechID": "CT_12",
        "improvised": false,
        "url": "",
        "clsrng": true,
        "armed": true,
        "templateID": "ITEMTPL_390"
    },
    {
        "name": "War Flail",
        "combattech": "Polearms",
        "primeattr": "AGI/STR",
        "threshold": 15,
        "damage": "1W6",
        "bonus": 4,
        "at": -1,
        "pa": -1,
        "range": 3,
        "weight": "2Stn",
        "price": 50,
        "sf": 12,
        "primeattrID": "ATTR_6/ATTR_8",
        "combattechID": "CT_13",
        "improvised": false,
        "url": "",
        "clsrng": true,
        "armed": true,
        "templateID": "ITEMTPL_392"
    },
    {
        "name": "Boar Spear",
        "combattech": "Polearms",
        "primeattr": "AGI/STR",
        "threshold": 15,
        "damage": "1W6",
        "bonus": 5,
        "at": 0,
        "pa": -1,
        "range": 3,
        "weight": "1,75Stn",
        "price": 100,
        "sf": 12,
        "primeattrID": "ATTR_6/ATTR_8",
        "combattechID": "CT_13",
        "improvised": false,
        "url": "",
        "clsrng": true,
        "armed": true,
        "templateID": "ITEMTPL_478"
    },
    {
        "name": "Scythe",
        "combattech": "Polearms",
        "primeattr": "AGI/STR",
        "threshold": 16,
        "damage": "1W6",
        "bonus": 3,
        "at": -2,
        "pa": -1,
        "range": 3,
        "weight": "3,5Stn",
        "price": 40,
        "sf": 12,
        "primeattrID": "ATTR_6/ATTR_8",
        "combattechID": "CT_13",
        "improvised": true,
        "url": "",
        "clsrng": true,
        "armed": true,
        "templateID": "ITEMTPL_394"
    },
    {
        "name": "War Scythe",
        "combattech": "Polearms",
        "primeattr": "AGI/STR",
        "threshold": 16,
        "damage": "1W6",
        "bonus": 5,
        "at": -1,
        "pa": -1,
        "range": 3,
        "weight": "1,75Stn",
        "price": 60,
        "sf": 12,
        "primeattrID": "ATTR_6/ATTR_8",
        "combattechID": "CT_13",
        "improvised": false,
        "url": "",
        "clsrng": true,
        "armed": true,
        "templateID": "ITEMTPL_395"
    },
    {
        "name": "Woodcutter’s Axe",
        "combattech": "Two-Handed Impact Weapons",
        "primeattr": "STR",
        "threshold": 13,
        "damage": "2W6",
        "bonus": 1,
        "at": 0,
        "pa": -4,
        "range": 2,
        "weight": "4Stn",
        "price": 80,
        "sf": 12,
        "primeattrID": "ATTR_8",
        "combattechID": "CT_15",
        "improvised": true,
        "url": "",
        "clsrng": true,
        "armed": true,
        "templateID": "ITEMTPL_158"
    },
    {
        "name": "Punt Axe",
        "combattech": "Two-Handed Impact Weapons",
        "primeattr": "STR",
        "threshold": 13,
        "damage": "1W6",
        "bonus": 4,
        "at": 0,
        "pa": -2,
        "range": 2,
        "weight": "3Stn",
        "price": 40,
        "sf": 12,
        "primeattrID": "ATTR_8",
        "combattechID": "CT_15",
        "improvised": true,
        "url": "",
        "clsrng": true,
        "armed": true,
        "templateID": "ITEMTPL_480"
    },
    {
        "name": "Nostrianer",
        "combattech": "Two-Handed Swords",
        "primeattr": "STR",
        "threshold": 14,
        "damage": "2W6",
        "bonus": 5,
        "at": 0,
        "pa": -4,
        "range": 2,
        "weight": "3,25Stn",
        "price": 400,
        "sf": 12,
        "primeattrID": "ATTR_8",
        "combattechID": "CT_16",
        "improvised": false,
        "url": "",
        "clsrng": true,
        "armed": true,
        "templateID": "ITEMTPL_482"
    },
    {
        "name": "Tournament Great Sword",
        "combattech": "Two-Handed Swords",
        "primeattr": "AGI/STR",
        "threshold": 16,
        "damage": "1W6",
        "bonus": 3,
        "at": 0,
        "pa": -2,
        "range": 2,
        "weight": "2,25Stn",
        "price": 40,
        "sf": 12,
        "primeattrID": "ATTR_6/ATTR_8",
        "combattechID": "CT_16",
        "improvised": false,
        "url": "",
        "clsrng": true,
        "armed": true,
        "templateID": "ITEMTPL_396"
    },
    {
        "name": "Oakhavener",
        "combattech": "Two-Handed Swords",
        "primeattr": "STR",
        "threshold": 14,
        "damage": "2W6",
        "bonus": 5,
        "at": 0,
        "pa": -4,
        "range": 2,
        "weight": "3,5Stn",
        "price": 440,
        "sf": 12,
        "primeattrID": "ATTR_8",
        "combattechID": "CT_16",
        "improvised": false,
        "url": "",
        "clsrng": true,
        "armed": true,
        "templateID": "ITEMTPL_546"
    },
    {
        "name": "Harmlyner",
        "combattech": "Two-Handed Swords",
        "primeattr": "STR",
        "threshold": 14,
        "damage": "2W6",
        "bonus": 5,
        "at": 0,
        "pa": -4,
        "range": 2,
        "weight": "3,5Stn",
        "price": 440,
        "sf": 12,
        "primeattrID": "ATTR_8",
        "combattechID": "CT_16",
        "improvised": false,
        "url": "",
        "clsrng": true,
        "armed": true,
        "templateID": "ITEMTPL_547"
    },
    {
        "name": "Andergaster",
        "combattech": "Two-Handed Swords",
        "primeattr": "STR",
        "threshold": 14,
        "damage": "2W6",
        "bonus": 5,
        "at": 0,
        "pa": -4,
        "range": 2,
        "weight": "3,25Stn",
        "price": 400,
        "sf": 12,
        "primeattrID": "ATTR_8",
        "combattechID": "CT_16",
        "improvised": false,
        "url": "",
        "clsrng": true,
        "armed": true,
        "templateID": "ITEMTPL_481"
    },
    {
        "name": "Andergastan Long Sword",
        "combattech": "Swords",
        "primeattr": "AGI/STR",
        "threshold": 15,
        "damage": "1W6",
        "bonus": 4,
        "at": 0,
        "pa": 0,
        "range": 2,
        "weight": "1,25Stn",
        "price": 200,
        "sf": 12,
        "primeattrID": "ATTR_6/ATTR_8",
        "combattechID": "CT_12",
        "improvised": false,
        "url": "",
        "clsrng": true,
        "armed": true,
        "templateID": "ITEMTPL_548"
    },
    {
        "name": "Nostrian Long Sword",
        "combattech": "Swords",
        "primeattr": "AGI/STR",
        "threshold": 15,
        "damage": "1W6",
        "bonus": 4,
        "at": 0,
        "pa": 0,
        "range": 2,
        "weight": "0,75Stn",
        "price": 200,
        "sf": 12,
        "primeattrID": "ATTR_6/ATTR_8",
        "combattechID": "CT_12",
        "improvised": false,
        "url": "",
        "clsrng": true,
        "armed": true,
        "templateID": "ITEMTPL_549"
    },
    {
        "name": "Battle-axe (Warring Kingdoms variant)",
        "combattech": "Impact Weapons",
        "primeattr": "STR",
        "threshold": 14,
        "damage": "1W6",
        "bonus": 4,
        "at": 0,
        "pa": -1,
        "range": 2,
        "weight": "1,5Stn",
        "price": 105,
        "sf": 12,
        "primeattrID": "ATTR_8",
        "combattechID": "CT_5",
        "improvised": false,
        "url": "",
        "clsrng": true,
        "armed": true,
        "templateID": "ITEMTPL_550"
    },
    {
        "name": "Mace (Warring Kingdoms variant)",
        "combattech": "Impact Weapons",
        "primeattr": "STR",
        "threshold": 14,
        "damage": "1W6",
        "bonus": 4,
        "at": 0,
        "pa": -1,
        "range": 2,
        "weight": "1,5Stn",
        "price": 105,
        "sf": 12,
        "primeattrID": "ATTR_8",
        "combattechID": "CT_5",
        "improvised": false,
        "url": "",
        "clsrng": true,
        "armed": true,
        "templateID": "ITEMTPL_551"
    },
    {
        "name": "Tournament Shield",
        "combattech": "Shields",
        "primeattr": "STR",
        "threshold": 16,
        "damage": "1W6",
        "at": -4,
        "pa": 1,
        "range": 1,
        "weight": "3,5Stn",
        "price": 30,
        "sf": 12,
        "primeattrID": "ATTR_8",
        "combattechID": "CT_10",
        "improvised": false,
        "url": "",
        "clsrng": true,
        "armed": true
    },
    {
        "name": "Druid Dagger (Flint)",
        "combattech": "Daggers",
        "primeattr": "AGI",
        "threshold": 15,
        "damage": "1W6",
        "bonus": 1,
        "at": -1,
        "pa": 0,
        "range": 1,
        "weight": "0,5Stn",
        "price": 60,
        "sf": 12,
        "primeattrID": "ATTR_6",
        "combattechID": "CT_3",
        "improvised": false,
        "url": "",
        "clsrng": true,
        "armed": true
    },
    {
        "name": "Mage’s Staff Made from Stone Oak Wood",
        "combattech": "Polearms",
        "primeattr": "AGI/STR",
        "threshold": 16,
        "damage": "1W6",
        "bonus": 2,
        "at": -1,
        "pa": 2,
        "range": 3,
        "weight": "1Stn",
        "price": 380,
        "sf": 12,
        "primeattrID": "ATTR_6/ATTR_8",
        "combattechID": "CT_13",
        "improvised": false,
        "url": "",
        "clsrng": true,
        "armed": true
    },
    {
        "name": "Beil",
        "combattech": "Impact Weapons",
        "primeattr": "STR",
        "threshold": 14,
        "damage": "1W6",
        "bonus": 2,
        "at": -1,
        "pa": -2,
        "range": 2,
        "weight": "0,75Stn",
        "price": 20,
        "sf": 12,
        "primeattrID": "ATTR_8",
        "combattechID": "CT_5",
        "improvised": false,
        "url": "index.php/beil-handaxt-i.html",
        "clsrng": true,
        "armed": true
    },
    {
        "name": "Handaxt",
        "combattech": "Impact Weapons",
        "primeattr": "STR",
        "threshold": 14,
        "damage": "1W6",
        "bonus": 2,
        "at": -1,
        "pa": -2,
        "range": 2,
        "weight": "0,75Stn",
        "price": 20,
        "sf": 12,
        "primeattrID": "ATTR_8",
        "combattechID": "CT_5",
        "improvised": false,
        "url": "index.php/beil-handaxt-i.html",
        "clsrng": true,
        "armed": true
    },
    {
        "name": "Torch",
        "combattech": "Impact Weapons",
        "primeattr": "STR",
        "threshold": 15,
        "damage": "1W6",
        "at": -1,
        "pa": -2,
        "range": 2,
        "weight": "0,5Stn",
        "sf": 12,
        "primeattrID": "ATTR_8",
        "combattechID": "CT_5",
        "improvised": true,
        "url": "index.php/fackel-i.html",
        "clsrng": true,
        "armed": true,
        "templateID": "ITEMTPL_182"
    },
    {
        "name": "Rolling Pin",
        "combattech": "Impact Weapons",
        "primeattr": "STR",
        "threshold": 14,
        "damage": "1W6",
        "bonus": 1,
        "at": -1,
        "pa": -2,
        "range": 2,
        "weight": "0,5Stn",
        "price": 10,
        "sf": 12,
        "primeattrID": "ATTR_8",
        "combattechID": "CT_5",
        "improvised": true,
        "url": "",
        "clsrng": true,
        "armed": true
    },
    {
        "name": "Rod-Style Rolling Pin",
        "combattech": "Impact Weapons",
        "primeattr": "STR",
        "threshold": 14,
        "damage": "1W6",
        "bonus": 1,
        "at": -1,
        "pa": -2,
        "range": 2,
        "weight": "0,5Stn",
        "price": 10,
        "sf": 12,
        "primeattrID": "ATTR_8",
        "combattechID": "CT_5",
        "improvised": true,
        "url": "",
        "clsrng": true,
        "armed": true
    },
    {
        "name": "Schmiedehammer",
        "combattech": "Impact Weapons",
        "primeattr": "STR",
        "threshold": 14,
        "damage": "1W6",
        "bonus": 3,
        "at": 0,
        "pa": -3,
        "range": 2,
        "weight": "1,25Stn",
        "price": 100,
        "sf": 12,
        "primeattrID": "ATTR_8",
        "combattechID": "CT_5",
        "improvised": true,
        "url": "index.php/schmiedehammer-i.html",
        "clsrng": true,
        "armed": true,
        "templateID": "ITEMTPL_383"
    },
    {
        "name": "Sichel",
        "combattech": "Impact Weapons",
        "primeattr": "STR",
        "threshold": 15,
        "damage": "1W6",
        "bonus": 2,
        "at": -1,
        "pa": -2,
        "range": 1,
        "weight": "0,5Stn",
        "price": 10,
        "sf": 12,
        "primeattrID": "ATTR_8",
        "combattechID": "CT_5",
        "improvised": true,
        "url": "index.php/sichel-i.html",
        "clsrng": true,
        "armed": true,
        "templateID": "ITEMTPL_384"
    },
    {
        "name": "Fuhrmannspeitsche",
        "combattech": "Peitschen",
        "primeattr": "FF",
        "threshold": 16,
        "damage": "1W6",
        "at": 0,
        "range": 3,
        "weight": "3Stn",
        "price": 20,
        "sf": 12,
        "primeattrID": "ATTR_5",
        "combattechID": "CT_8",
        "improvised": false,
        "url": "index.php/fuhrmannspeitsche.html",
        "clsrng": true,
        "armed": true,
        "templateID": "ITEMTPL_386"
    },
    {
        "name": "Breitschwert",
        "combattech": "Swords",
        "primeattr": "AGI/STR",
        "threshold": 14,
        "damage": "1W6",
        "bonus": 4,
        "at": -1,
        "pa": -1,
        "range": 2,
        "weight": "1,5Stn",
        "price": 180,
        "sf": 12,
        "primeattrID": "ATTR_6/ATTR_8",
        "combattechID": "CT_12",
        "improvised": false,
        "url": "index.php/breitschwert.html",
        "clsrng": true,
        "armed": true,
        "templateID": "ITEMTPL_387"
    },
    {
        "name": "Parazonium",
        "combattech": "Swords",
        "primeattr": "AGI/STR",
        "threshold": 15,
        "damage": "1W6",
        "bonus": 3,
        "at": 0,
        "pa": -1,
        "range": 1,
        "weight": "0,75Stn",
        "price": 140,
        "sf": 12,
        "primeattrID": "ATTR_6/ATTR_8",
        "combattechID": "CT_12",
        "improvised": false,
        "url": "index.php/parazonium-zyklopaeisches-kurzschwert.html",
        "clsrng": true,
        "armed": true
    },
    {
        "name": "Scimshar",
        "combattech": "Swords",
        "primeattr": "AGI/STR",
        "threshold": 14,
        "damage": "1W6",
        "bonus": 2,
        "at": 0,
        "pa": -1,
        "range": 1,
        "weight": "0,75Stn",
        "price": 140,
        "sf": 12,
        "primeattrID": "ATTR_6/ATTR_8",
        "combattechID": "CT_12",
        "improvised": false,
        "url": "index.php/scimshar-tulamidisches-kurzschwert.html",
        "clsrng": true,
        "armed": true
    },
    {
        "name": "Dreschflegel",
        "combattech": "Polearms",
        "primeattr": "AGI/STR",
        "threshold": 15,
        "damage": "1W6",
        "bonus": 2,
        "at": -2,
        "pa": -1,
        "range": 3,
        "weight": "1,75Stn",
        "price": 30,
        "sf": 12,
        "primeattrID": "ATTR_6/ATTR_8",
        "combattechID": "CT_13",
        "improvised": true,
        "url": "index.php/dreschflegel-2h-i.html",
        "clsrng": true,
        "armed": true,
        "templateID": "ITEMTPL_149"
    },
    {
        "name": "Hirtenstab",
        "combattech": "Polearms",
        "primeattr": "AGI/STR",
        "threshold": 15,
        "damage": "1W6",
        "bonus": 1,
        "at": 0,
        "pa": 2,
        "range": 3,
        "weight": "0,75Stn",
        "price": 10,
        "sf": 12,
        "primeattrID": "ATTR_6/ATTR_8",
        "combattechID": "CT_13",
        "improvised": false,
        "url": "index.php/hirtenstab-2h.html",
        "clsrng": true,
        "armed": true,
        "templateID": "ITEMTPL_391"
    },
    {
        "name": "Kriegsflegel",
        "combattech": "Polearms",
        "primeattr": "AGI/STR",
        "threshold": 15,
        "damage": "1W6",
        "bonus": 4,
        "at": -1,
        "pa": -1,
        "range": 3,
        "weight": "2Stn",
        "price": 50,
        "sf": 12,
        "primeattrID": "ATTR_6/ATTR_8",
        "combattechID": "CT_13",
        "improvised": false,
        "url": "index.php/kriegsflegel-2h.html",
        "clsrng": true,
        "armed": true
    },
    {
        "name": "Pailos",
        "combattech": "Polearms",
        "primeattr": "AGI/STR",
        "threshold": 15,
        "damage": "2W6",
        "bonus": 3,
        "at": -1,
        "pa": -2,
        "range": 3,
        "weight": "4,5Stn",
        "price": 300,
        "sf": 12,
        "primeattrID": "ATTR_6/ATTR_8",
        "combattechID": "CT_13",
        "improvised": false,
        "url": "index.php/pailos-2h.html",
        "clsrng": true,
        "armed": true,
        "templateID": "ITEMTPL_393"
    },
    {
        "name": "Sense",
        "combattech": "Polearms",
        "primeattr": "AGI/STR",
        "threshold": 16,
        "damage": "1W6",
        "bonus": 3,
        "at": -2,
        "pa": -1,
        "range": 3,
        "weight": "1,75Stn",
        "price": 40,
        "sf": 12,
        "primeattrID": "ATTR_6/ATTR_8",
        "combattechID": "CT_13",
        "improvised": true,
        "url": "index.php/sense-2h-i.html",
        "clsrng": true,
        "armed": true
    },
    {
        "name": "Sturmsense",
        "combattech": "Polearms",
        "primeattr": "AGI/STR",
        "threshold": 16,
        "damage": "1W6",
        "bonus": 5,
        "at": -1,
        "pa": -1,
        "range": 3,
        "weight": "1,75Stn",
        "price": 60,
        "sf": 12,
        "primeattrID": "ATTR_6/ATTR_8",
        "combattechID": "CT_13",
        "improvised": false,
        "url": "index.php/sturmsense-2h.html",
        "clsrng": true,
        "armed": true
    },
    {
        "name": "Amazonensäbel",
        "combattech": "Swords",
        "primeattr": "AGI/STR",
        "threshold": 15,
        "damage": "1W6",
        "bonus": 4,
        "at": 0,
        "pa": 0,
        "range": 2,
        "weight": "2Stn",
        "price": 200,
        "sf": 12,
        "primeattrID": "ATTR_6/ATTR_8",
        "combattechID": "CT_12",
        "improvised": false,
        "url": "index.php/amazonensaebel.html",
        "clsrng": true,
        "armed": true,
        "templateID": "ITEMTPL_454"
    },
    {
        "name": "Faustschild",
        "combattech": "Shields",
        "primeattr": "STR",
        "threshold": 16,
        "damage": "1W6",
        "at": -3,
        "pa": 0,
        "range": 1,
        "weight": "1Stn",
        "price": 40,
        "sf": 12,
        "primeattrID": "ATTR_8",
        "combattechID": "CT_10",
        "improvised": false,
        "url": "index.php/faustschild.html",
        "clsrng": true,
        "armed": true,
        "templateID": "ITEMTPL_453"
    },
    {
        "name": "Glefe",
        "combattech": "Polearms",
        "primeattr": "AGI/STR",
        "threshold": 15,
        "damage": "1W6",
        "bonus": 5,
        "at": 0,
        "pa": -2,
        "range": 3,
        "weight": "2Stn",
        "price": 50,
        "sf": 12,
        "primeattrID": "ATTR_6/ATTR_8",
        "combattechID": "CT_13",
        "improvised": false,
        "url": "index.php/glefe-2h.html",
        "clsrng": true,
        "armed": true,
        "templateID": "ITEMTPL_456"
    },
    {
        "name": "Hakendolch",
        "combattech": "Daggers",
        "primeattr": "AGI",
        "threshold": 14,
        "damage": "1W6",
        "bonus": 1,
        "at": -1,
        "pa": 0,
        "range": 1,
        "weight": "1,25Stn",
        "price": 80,
        "sf": 12,
        "primeattrID": "ATTR_6",
        "combattechID": "CT_3",
        "improvised": false,
        "url": "index.php/hakendolch.html",
        "clsrng": true,
        "armed": true,
        "templateID": "ITEMTPL_443"
    },
    {
        "name": "Jagdmesser",
        "combattech": "Daggers",
        "primeattr": "AGI",
        "threshold": 14,
        "damage": "1W6",
        "bonus": 1,
        "at": 0,
        "pa": -2,
        "range": 1,
        "weight": "0,25Stn",
        "price": 50,
        "sf": 12,
        "primeattrID": "ATTR_6",
        "combattechID": "CT_3",
        "improvised": false,
        "url": "index.php/jagdmesser.html",
        "clsrng": true,
        "armed": true,
        "templateID": "ITEMTPL_444"
    },
    {
        "name": "Jagdspieß",
        "combattech": "Polearms",
        "primeattr": "AGI/STR",
        "threshold": 15,
        "damage": "1W6",
        "bonus": 5,
        "at": 0,
        "pa": -1,
        "range": 3,
        "weight": "1,75Stn",
        "price": 80,
        "sf": 12,
        "primeattrID": "ATTR_6/ATTR_8",
        "combattechID": "CT_13",
        "improvised": false,
        "url": "index.php/jagdspiess-2h.html",
        "clsrng": true,
        "armed": true,
        "templateID": "ITEMTPL_457"
    },
    {
        "name": "Katar",
        "combattech": "Daggers",
        "primeattr": "AGI",
        "threshold": 13,
        "damage": "1W6",
        "bonus": 1,
        "at": 0,
        "pa": -1,
        "range": 1,
        "weight": "1,25Stn",
        "price": 50,
        "sf": 12,
        "primeattrID": "ATTR_6",
        "combattechID": "CT_3",
        "improvised": false,
        "url": "index.php/katar.html",
        "clsrng": true,
        "armed": true,
        "templateID": "ITEMTPL_445"
    },
    {
        "name": "Mengbilar",
        "combattech": "Daggers",
        "primeattr": "AGI",
        "threshold": 14,
        "damage": "1W6",
        "bonus": 1,
        "at": 0,
        "pa": -2,
        "range": 1,
        "weight": "0,5Stn",
        "price": 120,
        "sf": 12,
        "primeattrID": "ATTR_6",
        "combattechID": "CT_3",
        "improvised": false,
        "url": "index.php/mengbilar.html",
        "clsrng": true,
        "armed": true,
        "templateID": "ITEMTPL_446"
    },
    {
        "name": "Nachtwind",
        "combattech": "Swords",
        "primeattr": "AGI/STR",
        "threshold": 15,
        "damage": "1W6",
        "bonus": 4,
        "at": 0,
        "pa": 0,
        "range": 2,
        "weight": "1,75Stn",
        "price": 250,
        "sf": 12,
        "primeattrID": "ATTR_6/ATTR_8",
        "combattechID": "CT_12",
        "improvised": false,
        "url": "index.php/nachtwind.html",
        "clsrng": true,
        "armed": true,
        "templateID": "ITEMTPL_455"
    },
    {
        "name": "Ochsenherde",
        "combattech": "Kettenwaffen",
        "primeattr": "STR",
        "threshold": 14,
        "damage": "2W6",
        "bonus": 6,
        "at": -2,
        "range": 2,
        "weight": "6Stn",
        "price": 260,
        "sf": 12,
        "primeattrID": "ATTR_8",
        "combattechID": "CT_6",
        "improvised": false,
        "url": "index.php/ochsenherde-2h.html",
        "clsrng": true,
        "armed": true,
        "templateID": "ITEMTPL_449"
    },
    {
        "name": "Ogerfänger",
        "combattech": "Daggers",
        "primeattr": "AGI",
        "threshold": 14,
        "damage": "1W6",
        "bonus": 2,
        "at": 0,
        "pa": -1,
        "range": 1,
        "weight": "1Stn",
        "price": 100,
        "sf": 12,
        "primeattrID": "ATTR_6",
        "combattechID": "CT_3",
        "improvised": false,
        "url": "index.php/ogerfaenger.html",
        "clsrng": true,
        "armed": true,
        "templateID": "ITEMTPL_447"
    },
    {
        "name": "Ogerschelle",
        "combattech": "Kettenwaffen",
        "primeattr": "STR",
        "threshold": 14,
        "damage": "2W6",
        "bonus": 2,
        "at": -2,
        "range": 2,
        "weight": "4Stn",
        "price": 180,
        "sf": 12,
        "primeattrID": "ATTR_8",
        "combattechID": "CT_6",
        "improvised": false,
        "url": "index.php/ogerschelle.html",
        "clsrng": true,
        "armed": true,
        "templateID": "ITEMTPL_450"
    },
    {
        "name": "Orchidee",
        "combattech": "Brawling",
        "primeattr": "AGI/STR",
        "threshold": 15,
        "damage": "1W6",
        "bonus": 2,
        "at": 0,
        "pa": -1,
        "range": 1,
        "weight": "1Stn",
        "price": 60,
        "sf": 12,
        "primeattrID": "ATTR_6/ATTR_8",
        "combattechID": "CT_9",
        "improvised": false,
        "url": "index.php/orchidee.html",
        "clsrng": true,
        "armed": true,
        "templateID": "ITEMTPL_451"
    },
    {
        "name": "Panzerarm",
        "combattech": "Brawling",
        "primeattr": "AGI/STR",
        "threshold": 15,
        "damage": "1W6",
        "bonus": 1,
        "at": 0,
        "pa": 0,
        "range": 1,
        "weight": "1Stn",
        "price": 70,
        "sf": 12,
        "primeattrID": "ATTR_6/ATTR_8",
        "combattechID": "CT_9",
        "improvised": false,
        "url": "index.php/panzerarm.html",
        "clsrng": true,
        "armed": true,
        "templateID": "ITEMTPL_452"
    },
    {
        "name": "Richtschwert",
        "combattech": "Swords",
        "primeattr": "STR",
        "threshold": 14,
        "damage": "2W6",
        "bonus": 6,
        "at": -2,
        "pa": -3,
        "range": 2,
        "weight": "5Stn",
        "price": 600,
        "sf": 12,
        "primeattrID": "ATTR_8",
        "combattechID": "CT_12",
        "improvised": true,
        "url": "index.php/richtschwert-2h-i.html",
        "clsrng": true,
        "armed": true,
        "templateID": "ITEMTPL_460"
    },
    {
        "name": "Schnitter",
        "combattech": "Polearms",
        "primeattr": "AGI/STR",
        "threshold": 15,
        "damage": "1W6",
        "bonus": 5,
        "at": -1,
        "pa": -1,
        "range": 3,
        "weight": "2Stn",
        "price": 80,
        "sf": 12,
        "primeattrID": "ATTR_6/ATTR_8",
        "combattechID": "CT_13",
        "improvised": false,
        "url": "index.php/schnitter-2h.html",
        "clsrng": true,
        "armed": true,
        "templateID": "ITEMTPL_458"
    },
    {
        "name": "Stockdegen",
        "combattech": "Fencing",
        "primeattr": "AGI",
        "threshold": 15,
        "damage": "1W6",
        "bonus": 2,
        "at": 1,
        "pa": 0,
        "range": 2,
        "weight": "1Stn",
        "price": 350,
        "sf": 12,
        "primeattrID": "ATTR_6",
        "combattechID": "CT_4",
        "improvised": false,
        "url": "index.php/stockdegen.html",
        "clsrng": true,
        "armed": true,
        "templateID": "ITEMTPL_448"
    },
    {
        "name": "WarunkerHammer",
        "combattech": "Two-Handed Impact Weapons",
        "primeattr": "STR",
        "threshold": 14,
        "damage": "1W6",
        "bonus": 6,
        "at": 0,
        "pa": -3,
        "range": 3,
        "weight": "3,75Stn",
        "price": 300,
        "sf": 12,
        "primeattrID": "ATTR_8",
        "combattechID": "CT_15",
        "improvised": false,
        "url": "index.php/warunker-hammer-2h.html",
        "clsrng": true,
        "armed": true,
        "templateID": "ITEMTPL_459"
    },
    {
        "name": "Broom",
        "combattech": "Impact Weapons",
        "primeattr": "STR",
        "threshold": 15,
        "damage": "1W6",
        "bonus": 2,
        "at": -1,
        "pa": -3,
        "range": 2,
        "weight": "0,75Stn",
        "sf": 12,
        "primeattrID": "ATTR_8",
        "combattechID": "CT_5",
        "improvised": true,
        "url": "",
        "clsrng": true,
        "armed": true,
        "templateID": "ITEMTPL_146"
    },
    {
        "name": "Frying Pan",
        "combattech": "Impact Weapons",
        "primeattr": "STR",
        "threshold": 15,
        "damage": "1W6",
        "bonus": 3,
        "at": -1,
        "pa": -3,
        "range": 1,
        "weight": "2Stn",
        "price": 12,
        "sf": 12,
        "primeattrID": "ATTR_8",
        "combattechID": "CT_5",
        "improvised": true,
        "url": "",
        "clsrng": true,
        "armed": true
    },
    {
        "name": "Frying Pan, hot",
        "combattech": "Impact Weapons",
        "primeattr": "STR",
        "threshold": 15,
        "damage": "1W6",
        "bonus": 4,
        "at": -2,
        "pa": -3,
        "range": 1,
        "weight": "2Stn",
        "price": 12,
        "sf": 12,
        "primeattrID": "ATTR_8",
        "combattechID": "CT_5",
        "improvised": true,
        "url": "",
        "clsrng": true,
        "armed": true
    },
    {
        "name": "Bottle",
        "combattech": "Impact Weapons",
        "primeattr": "STR",
        "threshold": 16,
        "damage": "1W6",
        "bonus": 1,
        "at": -1,
        "pa": -3,
        "range": 1,
        "weight": "",
        "sf": 12,
        "primeattrID": "ATTR_8",
        "combattechID": "CT_5",
        "improvised": true,
        "url": "",
        "clsrng": true,
        "armed": true
    },
    {
        "name": "Bottle, broken",
        "combattech": "Impact Weapons",
        "primeattr": "STR",
        "threshold": 16,
        "damage": "1W6",
        "bonus": 2,
        "at": -1,
        "pa": -4,
        "range": 1,
        "weight": "",
        "sf": 12,
        "primeattrID": "ATTR_8",
        "combattechID": "CT_5",
        "improvised": true,
        "url": "",
        "clsrng": true,
        "armed": true
    },
    {
        "name": "Chair",
        "combattech": "Impact Weapons",
        "primeattr": "STR",
        "threshold": 15,
        "damage": "1W6",
        "bonus": 3,
        "at": -2,
        "pa": -2,
        "range": 2,
        "weight": "",
        "sf": 12,
        "primeattrID": "ATTR_8",
        "combattechID": "CT_5",
        "improvised": true,
        "url": "",
        "clsrng": true,
        "armed": true
    },
    {
        "name": "Chair leg",
        "combattech": "Impact Weapons",
        "primeattr": "STR",
        "threshold": 14,
        "damage": "1W6",
        "bonus": 2,
        "at": -1,
        "pa": -3,
        "range": 2,
        "weight": "",
        "sf": 12,
        "primeattrID": "ATTR_8",
        "combattechID": "CT_5",
        "improvised": true,
        "url": "",
        "clsrng": true,
        "armed": true
    },
    {
        "name": "Table",
        "combattech": "Impact Weapons",
        "primeattr": "STR",
        "threshold": 17,
        "damage": "1W6",
        "bonus": 4,
        "at": -4,
        "pa": -1,
        "range": 2,
        "weight": "",
        "sf": 12,
        "primeattrID": "ATTR_8",
        "combattechID": "CT_5",
        "improvised": true,
        "url": "index.php/tisch-i.html",
        "clsrng": true,
        "armed": true
    },
    {
        "name": "Spit",
        "combattech": "Impact Weapons",
        "primeattr": "AGI/STR",
        "threshold": 14,
        "damage": "1W6",
        "bonus": 1,
        "at": -1,
        "pa": -2,
        "range": 2,
        "weight": "3Stn",
        "price": 16,
        "sf": 12,
        "primeattrID": "ATTR_6/ATTR_8",
        "combattechID": "CT_5",
        "improvised": true,
        "url": "",
        "clsrng": true,
        "armed": true,
        "templateID": "ITEMTPL_147"
    },
    {
        "name": "Crowbar",
        "combattech": "Impact Weapons",
        "primeattr": "STR",
        "threshold": 14,
        "damage": "1W6",
        "bonus": 2,
        "at": -1,
        "pa": -3,
        "range": 2,
        "weight": "5Stn",
        "price": 26,
        "sf": 12,
        "primeattrID": "ATTR_8",
        "combattechID": "CT_5",
        "improvised": true,
        "url": "",
        "clsrng": true,
        "armed": true,
        "templateID": "ITEMTPL_221"
    },
    {
        "name": "Soap with cloth",
        "combattech": "Kettenwaffen",
        "primeattr": "STR",
        "threshold": 14,
        "damage": "1W3",
        "at": -1,
        "range": 2,
        "weight": "0,5Stn",
        "price": 1,
        "sf": 12,
        "primeattrID": "ATTR_8",
        "combattechID": "CT_6",
        "improvised": true,
        "url": "index.php/seife-mit-tuch-i.html",
        "clsrng": true,
        "armed": true,
        "templateID": "ITEMTPL_441"
    },
    {
        "name": "Grappling Hook with Rope",
        "combattech": "Kettenwaffen",
        "primeattr": "STR",
        "threshold": 14,
        "damage": "1W6",
        "bonus": 1,
        "at": -2,
        "range": 3,
        "weight": "1,5Stn",
        "sf": 12,
        "primeattrID": "ATTR_8",
        "combattechID": "CT_6",
        "improvised": true,
        "url": "",
        "clsrng": true,
        "armed": true,
        "templateID": "ITEMTPL_442"
    },
    {
        "name": "Pry bar",
        "combattech": "Two-Handed Impact Weapons",
        "primeattr": "STR",
        "threshold": 13,
        "damage": "1W6",
        "bonus": 3,
        "at": -1,
        "pa": -3,
        "range": 2,
        "weight": "6Stn",
        "price": 38,
        "sf": 12,
        "primeattrID": "ATTR_8",
        "combattechID": "CT_15",
        "improvised": true,
        "url": "",
        "clsrng": true,
        "armed": true,
        "templateID": "ITEMTPL_408"
    },
    {
        "name": "Spade",
        "combattech": "Two-Handed Impact Weapons",
        "primeattr": "STR",
        "threshold": 13,
        "damage": "1W6",
        "bonus": 4,
        "at": -2,
        "pa": -4,
        "range": 2,
        "weight": "2Stn",
        "sf": 12,
        "primeattrID": "ATTR_8",
        "combattechID": "CT_15",
        "improvised": true,
        "url": "",
        "clsrng": true,
        "armed": true,
        "templateID": "ITEMTPL_174"
    },
    {
        "name": "pickaxe",
        "combattech": "Two-Handed Impact Weapons",
        "primeattr": "STR",
        "threshold": 13,
        "damage": "1W6",
        "bonus": 5,
        "at": -1,
        "pa": -5,
        "range": 2,
        "weight": "2,75Stn",
        "price": 20,
        "sf": 12,
        "primeattrID": "ATTR_8",
        "combattechID": "CT_15",
        "improvised": true,
        "url": "",
        "clsrng": true,
        "armed": true,
        "templateID": "ITEMTPL_175"
    },
    {
        "name": "Shakagra-Giftdolch",
        "combattech": "Daggers",
        "primeattr": "AGI",
        "threshold": 14,
        "damage": "1W6",
        "bonus": 1,
        "at": 0,
        "pa": 0,
        "range": 1,
        "weight": "0,4Stn",
        "price": 80,
        "sf": 12,
        "primeattrID": "ATTR_6",
        "combattechID": "CT_3",
        "improvised": false,
        "url": "index.php/shakagra-giftdolch.html",
        "clsrng": true,
        "armed": true
    },
    {
        "name": "Shakagra-Hammer",
        "combattech": "Impact Weapons",
        "primeattr": "STR",
        "threshold": 14,
        "damage": "1W6",
        "bonus": 4,
        "at": 0,
        "pa": -1,
        "range": 2,
        "weight": "1,25Stn",
        "price": 175,
        "sf": 12,
        "primeattrID": "ATTR_8",
        "combattechID": "CT_5",
        "improvised": false,
        "url": "index.php/shakagra-hammer.html",
        "clsrng": true,
        "armed": true
    },
    {
        "name": "Shakagra-Buckler",
        "combattech": "Shields",
        "primeattr": "STR",
        "threshold": 15,
        "damage": "1W6",
        "at": -3,
        "pa": 1,
        "range": 1,
        "weight": "3Stn",
        "price": 250,
        "sf": 12,
        "primeattrID": "ATTR_8",
        "combattechID": "CT_10",
        "improvised": false,
        "url": "index.php/shakagra-buckler.html",
        "clsrng": true,
        "armed": true
    },
    {
        "name": "Shakagra-Langschild",
        "combattech": "Shields",
        "primeattr": "STR",
        "threshold": 16,
        "damage": "1W6",
        "bonus": 1,
        "at": -5,
        "pa": 3,
        "range": 1,
        "weight": "5Stn",
        "price": 500,
        "sf": 12,
        "primeattrID": "ATTR_8",
        "combattechID": "CT_10",
        "improvised": false,
        "url": "index.php/shakagra-langschild.html",
        "clsrng": true,
        "armed": true
    },
    {
        "name": "Shakagra-Krummsäbel",
        "combattech": "Swords",
        "primeattr": "AGI/STR",
        "threshold": 15,
        "damage": "1W6",
        "bonus": 4,
        "at": 0,
        "pa": 0,
        "range": 2,
        "weight": "0,75Stn",
        "price": 200,
        "sf": 12,
        "primeattrID": "ATTR_6/ATTR_8",
        "combattechID": "CT_12",
        "improvised": false,
        "url": "index.php/shakagra-krummsaebel.html",
        "clsrng": true,
        "armed": true
    },
    {
        "name": "Shakagra-Schwert",
        "combattech": "Swords",
        "primeattr": "AGI/STR",
        "threshold": 15,
        "damage": "1W6",
        "bonus": 5,
        "at": 0,
        "pa": 0,
        "range": 2,
        "weight": "0,75Stn",
        "price": 200,
        "sf": 12,
        "primeattrID": "ATTR_6/ATTR_8",
        "combattechID": "CT_12",
        "improvised": false,
        "url": "index.php/shakagra-schwert.html",
        "clsrng": true,
        "armed": true
    },
    {
        "name": "Shakagra-Kriegshammer",
        "combattech": "Two-Handed Impact Weapons",
        "primeattr": "STR",
        "threshold": 13,
        "damage": "2W6",
        "bonus": 3,
        "at": 0,
        "pa": -3,
        "range": 2,
        "weight": "2Stn",
        "price": 250,
        "sf": 12,
        "primeattrID": "ATTR_8",
        "combattechID": "CT_15",
        "improvised": false,
        "url": "index.php/shakagra-kriegshammer-2h.html",
        "clsrng": true,
        "armed": true
    },
    {
        "name": "Bannschwert,klein",
        "combattech": "Daggers",
        "primeattr": "AGI",
        "threshold": 14,
        "damage": "1W6",
        "bonus": 1,
        "at": 0,
        "pa": 0,
        "range": 1,
        "weight": "0,5Stn",
        "price": 45,
        "sf": 12,
        "primeattrID": "ATTR_6",
        "combattechID": "CT_3",
        "improvised": false,
        "url": "index.php/bannschwert-klein.html",
        "clsrng": true,
        "armed": true
    },
    {
        "name": "Bannschwert,mittel",
        "combattech": "Swords",
        "primeattr": "AGI/STR",
        "threshold": 15,
        "damage": "1W6",
        "bonus": 4,
        "at": 0,
        "pa": 0,
        "range": 2,
        "weight": "1Stn",
        "price": 200,
        "sf": 12,
        "primeattrID": "ATTR_6/ATTR_8",
        "combattechID": "CT_12",
        "improvised": false,
        "url": "index.php/bannschwert-mittel.html",
        "clsrng": true,
        "armed": true
    },
    {
        "name": "Bannschwert,groß",
        "combattech": "Two-Handed Swords",
        "primeattr": "STR",
        "threshold": 14,
        "damage": "2W6",
        "bonus": 4,
        "at": 0,
        "pa": -3,
        "range": 2,
        "weight": "2,5Stn",
        "price": 360,
        "sf": 12,
        "primeattrID": "ATTR_8",
        "combattechID": "CT_16",
        "improvised": false,
        "url": "index.php/bannschwert-gross.html",
        "clsrng": true,
        "armed": true
    },
    {
        "name": "Zauberkugel",
        "combattech": "Two-Handed Impact Weapons",
        "primeattr": "STR",
        "threshold": 13,
        "damage": "1W6",
        "bonus": 1,
        "at": -1,
        "pa": -4,
        "range": 1,
        "weight": "2Stn",
        "price": 30,
        "sf": 12,
        "primeattrID": "ATTR_8",
        "combattechID": "CT_15",
        "improvised": false,
        "url": "index.php/zauberkugel-6550.html",
        "clsrng": true,
        "armed": true
    },
    {
        "name": "Zauberstecken,kurz",
        "combattech": "Impact Weapons",
        "primeattr": "STR",
        "threshold": 14,
        "damage": "1W6",
        "bonus": 1,
        "at": 0,
        "pa": -1,
        "range": 1,
        "weight": "0,75Stn",
        "price": 30,
        "sf": 12,
        "primeattrID": "ATTR_8",
        "combattechID": "CT_5",
        "improvised": false,
        "url": "index.php/zauberstecken-kurz.html",
        "clsrng": true,
        "armed": true
    },
    {
        "name": "Zauberstecken,mittel",
        "combattech": "Impact Weapons",
        "primeattr": "STR",
        "threshold": 14,
        "damage": "1W6",
        "bonus": 2,
        "at": 0,
        "pa": -1,
        "range": 2,
        "weight": "0,75Stn",
        "price": 45,
        "sf": 12,
        "primeattrID": "ATTR_8",
        "combattechID": "CT_5",
        "improvised": false,
        "url": "index.php/zauberstecken-mittel.html",
        "clsrng": true,
        "armed": true
    },
    {
        "name": "Zauberstecken,lang",
        "combattech": "Polearms",
        "primeattr": "AGI/STR",
        "threshold": 16,
        "damage": "1W6",
        "bonus": 2,
        "at": -1,
        "pa": 2,
        "range": 3,
        "weight": "0,75Stn",
        "price": 60,
        "sf": 12,
        "primeattrID": "ATTR_6/ATTR_8",
        "combattechID": "CT_13",
        "improvised": false,
        "url": "index.php/zauberstecken-lang-2h.html",
        "clsrng": true,
        "armed": true
    },
    {
        "name": "Laute",
        "combattech": "Impact Weapons",
        "primeattr": "STR",
        "threshold": 14,
        "damage": "1W6",
        "bonus": 1,
        "at": -1,
        "pa": -3,
        "range": 2,
        "weight": "2Stn",
        "price": 150,
        "sf": 12,
        "primeattrID": "ATTR_8",
        "combattechID": "CT_5",
        "improvised": true,
        "url": "index.php/laute-und-aehnliche-instrumente-i.html",
        "clsrng": true,
        "armed": true
    },
    {
        "name": "Flöte",
        "combattech": "Impact Weapons",
        "primeattr": "AGI",
        "threshold": 14,
        "damage": "1W6",
        "at": -1,
        "pa": -4,
        "range": 1,
        "weight": "0,25Stn",
        "price": 2,
        "sf": 12,
        "primeattrID": "ATTR_6",
        "combattechID": "CT_5",
        "improvised": true,
        "url": "index.php/floete-und-aehnliche-instrumente-i.html",
        "clsrng": true,
        "armed": true
    },
    {
        "name": "Angbarer Sappeursaxt",
        "combattech": "Impact Weapons",
        "primeattr": "STR",
        "threshold": 14,
        "damage": "1W6",
        "bonus": 3,
        "at": 0,
        "pa": -2,
        "range": 2,
        "weight": "1,25Stn",
        "price": 85,
        "sf": 999,
        "primeattrID": "ATTR_8",
        "combattechID": "CT_5",
        "improvised": false,
        "url": "index.php/angbarer-sappeursaxt.html",
        "clsrng": true,
        "armed": true
    },
    {
        "name": "Byakka",
        "combattech": "Impact Weapons",
        "primeattr": "STR",
        "threshold": 14,
        "damage": "1W6",
        "bonus": 5,
        "at": 0,
        "pa": -2,
        "range": 2,
        "weight": "3,25Stn",
        "price": 90,
        "sf": 999,
        "primeattrID": "ATTR_8",
        "combattechID": "CT_5",
        "improvised": false,
        "url": "index.php/byakka.html",
        "clsrng": true,
        "armed": true
    },
    {
        "name": "Dornenkeule",
        "combattech": "Impact Weapons",
        "primeattr": "STR",
        "threshold": 14,
        "damage": "1W6",
        "bonus": 4,
        "at": -1,
        "pa": -2,
        "range": 2,
        "weight": "1Stn",
        "price": 13,
        "sf": 999,
        "primeattrID": "ATTR_8",
        "combattechID": "CT_5",
        "improvised": false,
        "url": "index.php/dornenkeule.html",
        "clsrng": true,
        "armed": true
    },
    {
        "name": "Elenviner Reiterhammer",
        "combattech": "Impact Weapons",
        "primeattr": "STR",
        "threshold": 14,
        "damage": "1W6",
        "bonus": 4,
        "at": 0,
        "pa": -1,
        "range": 2,
        "weight": "2Stn",
        "price": 100,
        "sf": 999,
        "primeattrID": "ATTR_8",
        "combattechID": "CT_5",
        "improvised": false,
        "url": "index.php/elenviner-reiterhammer.html",
        "clsrng": true,
        "armed": true
    },
    {
        "name": "Fleischerbeil",
        "combattech": "Impact Weapons",
        "primeattr": "STR",
        "threshold": 14,
        "damage": "1W6",
        "bonus": 3,
        "at": -1,
        "pa": -3,
        "range": 2,
        "weight": "1Stn",
        "price": 25,
        "sf": 999,
        "primeattrID": "ATTR_8",
        "combattechID": "CT_5",
        "improvised": true,
        "url": "index.php/fleischerbeil-i.html",
        "clsrng": true,
        "armed": true,
        "templateID": "ITEMTPL_584"
    },
    {
        "name": "Knochenkeule",
        "combattech": "Impact Weapons",
        "primeattr": "STR",
        "threshold": 14,
        "damage": "1W6",
        "bonus": 1,
        "at": 0,
        "pa": -1,
        "range": 2,
        "weight": "0,5Stn",
        "price": 0.6,
        "sf": 999,
        "primeattrID": "ATTR_8",
        "combattechID": "CT_5",
        "improvised": false,
        "url": "index.php/knochenkeule.html",
        "clsrng": true,
        "armed": true
    },
    {
        "name": "Senaloscher Sehnenschneider",
        "combattech": "Impact Weapons",
        "primeattr": "STR",
        "threshold": 13,
        "damage": "1W6",
        "bonus": 3,
        "at": 0,
        "pa": -1,
        "range": 2,
        "weight": "2Stn",
        "price": 100,
        "sf": 999,
        "primeattrID": "ATTR_8",
        "combattechID": "CT_5",
        "improvised": false,
        "url": "index.php/senaloscher-sehnenschneider.html",
        "clsrng": true,
        "armed": true
    },
    {
        "name": "Lûrer Lindwurmschläger",
        "combattech": "Impact Weapons",
        "primeattr": "STR",
        "threshold": 14,
        "damage": "1W6",
        "bonus": 4,
        "at": 0,
        "pa": -1,
        "range": 2,
        "weight": "1Stn",
        "price": 90,
        "sf": 999,
        "primeattrID": "ATTR_8",
        "combattechID": "CT_5",
        "improvised": false,
        "url": "index.php/lurer-lindwurmschlaeger.html",
        "clsrng": true,
        "armed": true
    },
    {
        "name": "Zwergenskraja",
        "combattech": "Impact Weapons",
        "primeattr": "STR",
        "threshold": 13,
        "damage": "1W6",
        "bonus": 3,
        "at": 0,
        "pa": -1,
        "range": 2,
        "weight": "2Stn",
        "price": 100,
        "sf": 999,
        "primeattrID": "ATTR_8",
        "combattechID": "CT_5",
        "improvised": false,
        "url": "index.php/zwergenskraja.html",
        "clsrng": true,
        "armed": true,
        "templateID": "ITEMTPL_639"
    },
    {
        "name": "Charib’Yzz-Dolch",
        "combattech": "Daggers",
        "primeattr": "AGI/STR",
        "threshold": 15,
        "damage": "1W6",
        "bonus": 3,
        "at": 0,
        "pa": -1,
        "range": 2,
        "weight": "2Stn",
        "price": 60,
        "sf": 999,
        "primeattrID": "ATTR_6/ATTR_8",
        "combattechID": "CT_3",
        "improvised": false,
        "url": "index.php/Charib_Yzz-Dolch.html",
        "clsrng": true,
        "armed": true
    },
    {
        "name": "Schneiderschere",
        "combattech": "Daggers",
        "primeattr": "AGI/STR",
        "threshold": 16,
        "damage": "1W6",
        "bonus": 1,
        "at": -2,
        "pa": -3,
        "range": 1,
        "weight": "0,3Stn",
        "price": 7,
        "sf": 999,
        "primeattrID": "ATTR_6/ATTR_8",
        "combattechID": "CT_3",
        "improvised": true,
        "url": "index.php/schneiderschere-i.html",
        "clsrng": true,
        "armed": true
    },
    {
        "name": "Federmesser",
        "combattech": "Daggers",
        "primeattr": "AGI/STR",
        "threshold": 16,
        "damage": "1W6",
        "bonus": 1,
        "at": -1,
        "pa": -4,
        "range": 1,
        "weight": "0,2Stn",
        "price": 3,
        "sf": 999,
        "primeattrID": "ATTR_6/ATTR_8",
        "combattechID": "CT_3",
        "improvised": true,
        "url": "index.php/federmesser-i.html",
        "clsrng": true,
        "armed": true,
        "templateID": "ITEMTPL_283"
    },
    {
        "name": "Elfendolch",
        "combattech": "Daggers",
        "primeattr": "AGI",
        "threshold": 16,
        "damage": "1W6",
        "bonus": 1,
        "at": 0,
        "pa": 0,
        "range": 1,
        "weight": "0,5Stn",
        "price": 100,
        "sf": 999,
        "primeattrID": "ATTR_6",
        "combattechID": "CT_3",
        "improvised": false,
        "url": "index.php/elfendolch.html",
        "clsrng": true,
        "armed": true,
        "templateID": "ITEMTPL_716"
    },
    {
        "name": "Langdolch",
        "combattech": "Daggers",
        "primeattr": "AGI",
        "threshold": 14,
        "damage": "1W6",
        "bonus": 1,
        "at": 0,
        "pa": 0,
        "range": 1,
        "weight": "0,5Stn",
        "price": 55,
        "sf": 999,
        "primeattrID": "ATTR_6",
        "combattechID": "CT_3",
        "improvised": false,
        "url": "index.php/langdolch.html",
        "clsrng": true,
        "armed": true
    },
    {
        "name": "Firunsmesser",
        "combattech": "Daggers",
        "primeattr": "AGI",
        "threshold": 14,
        "damage": "1W6",
        "bonus": 1,
        "at": 0,
        "pa": -2,
        "range": 1,
        "weight": "0,5Stn",
        "price": 100,
        "sf": 999,
        "primeattrID": "ATTR_6",
        "combattechID": "CT_3",
        "improvised": false,
        "url": "index.php/firunmesser.html",
        "clsrng": true,
        "armed": true,
        "templateID": "ITEMTPL_511"
    },
    {
        "name": "Scheibendolch",
        "combattech": "Daggers",
        "primeattr": "AGI",
        "threshold": 15,
        "damage": "1W6",
        "bonus": 2,
        "at": 0,
        "pa": -3,
        "range": 1,
        "weight": "1Stn",
        "price": 60,
        "sf": 999,
        "primeattrID": "ATTR_6",
        "combattechID": "CT_3",
        "improvised": false,
        "url": "index.php/scheibendolch.html",
        "clsrng": true,
        "armed": true
    },
    {
        "name": "Opferdolch",
        "combattech": "Daggers",
        "primeattr": "AGI",
        "threshold": 14,
        "damage": "1W6",
        "bonus": 2,
        "at": 0,
        "pa": -1,
        "range": 1,
        "weight": "0,5Stn",
        "price": 50,
        "sf": 999,
        "primeattrID": "ATTR_6",
        "combattechID": "CT_3",
        "improvised": false,
        "url": "index.php/opferdolch.html",
        "clsrng": true,
        "armed": true
    },
    {
        "name": "Schere",
        "combattech": "Daggers",
        "primeattr": "AGI/STR",
        "threshold": 15,
        "damage": "1W6",
        "bonus": 1,
        "at": -2,
        "pa": -4,
        "range": 1,
        "weight": "0,25Stn",
        "price": 5,
        "sf": 999,
        "primeattrID": "ATTR_6/ATTR_8",
        "combattechID": "CT_3",
        "improvised": true,
        "url": "index.php/schere.html",
        "clsrng": true,
        "armed": true,
        "templateID": "ITEMTPL_171"
    },
    {
        "name": "Windhager Drachenmesser",
        "combattech": "Daggers",
        "primeattr": "AGI",
        "threshold": 14,
        "damage": "1W6",
        "bonus": 2,
        "at": 0,
        "pa": -1,
        "range": 1,
        "weight": "0,75Stn",
        "price": 60,
        "sf": 999,
        "primeattrID": "ATTR_6",
        "combattechID": "CT_3",
        "improvised": false,
        "url": "index.php/windhager-drachenmesser.html",
        "clsrng": true,
        "armed": true,
        "templateID": "ITEMTPL_525"
    },
    {
        "name": "Schlachtermesser",
        "combattech": "Daggers",
        "primeattr": "",
        "threshold": 99,
        "damage": "1W6",
        "bonus": 2,
        "at": -1,
        "pa": -3,
        "range": 1,
        "weight": "1Stn",
        "price": 40,
        "sf": 999,
        "primeattrID": "",
        "combattechID": "CT_3",
        "improvised": true,
        "url": "index.php/schlachtermesser.html",
        "clsrng": true,
        "armed": true,
        "templateID": "ITEMTPL_715"
    },
    {
        "name": "Aleeza",
        "combattech": "Fencing",
        "primeattr": "AGI",
        "threshold": 16,
        "damage": "1W6",
        "bonus": 2,
        "at": 1,
        "pa": 1,
        "range": 2,
        "weight": "0,5Stn",
        "price": 250,
        "sf": 999,
        "primeattrID": "ATTR_6",
        "combattechID": "CT_4",
        "improvised": false,
        "url": "index.php/aleeza.html",
        "clsrng": true,
        "armed": true,
        "templateID": "ITEMTPL_717"
    },
    {
        "name": "Degen",
        "combattech": "Fencing",
        "primeattr": "AGI",
        "threshold": 15,
        "damage": "1W6",
        "bonus": 3,
        "at": 0,
        "pa": 1,
        "range": 2,
        "weight": "0,75Stn",
        "price": 150,
        "sf": 999,
        "primeattrID": "ATTR_6",
        "combattechID": "CT_4",
        "improvised": false,
        "url": "index.php/degen.html",
        "clsrng": true,
        "armed": true,
        "templateID": "ITEMTPL_608"
    },
    {
        "name": "Magierdegen",
        "combattech": "Fencing",
        "primeattr": "AGI",
        "threshold": 16,
        "damage": "1W6",
        "bonus": 2,
        "at": 0,
        "pa": 2,
        "range": 2,
        "weight": "0,5Stn",
        "price": 250,
        "sf": 999,
        "primeattrID": "ATTR_6",
        "combattechID": "CT_4",
        "improvised": false,
        "url": "index.php/magierdegen.html",
        "clsrng": true,
        "armed": true
    },
    {
        "name": "Druidensichel",
        "combattech": "Impact Weapons",
        "primeattr": "STR",
        "threshold": 15,
        "damage": "1W6",
        "bonus": 2,
        "at": -2,
        "pa": -2,
        "range": 1,
        "weight": "0,5Stn",
        "price": 70,
        "sf": 999,
        "primeattrID": "ATTR_8",
        "combattechID": "CT_5",
        "improvised": false,
        "url": "index.php/druidensichel.html",
        "clsrng": true,
        "armed": true
    },
    {
        "name": "Handspiegel",
        "combattech": "Impact Weapons",
        "primeattr": "STR",
        "threshold": 16,
        "damage": "1W6",
        "bonus": 1,
        "at": -2,
        "pa": -3,
        "range": 1,
        "weight": "0,5Stn",
        "price": 60,
        "sf": 999,
        "primeattrID": "ATTR_8",
        "combattechID": "CT_5",
        "improvised": true,
        "url": "index.php/handspiegel.html",
        "clsrng": true,
        "armed": true,
        "templateID": "ITEMTPL_335"
    },
    {
        "name": "Holzhammer",
        "combattech": "Impact Weapons",
        "primeattr": "STR",
        "threshold": 14,
        "damage": "1W6",
        "bonus": 2,
        "at": -1,
        "pa": -3,
        "range": 1,
        "weight": "0,5Stn",
        "price": 3,
        "sf": 999,
        "primeattrID": "ATTR_8",
        "combattechID": "CT_5",
        "improvised": true,
        "url": "index.php/holzhammer-i.html",
        "clsrng": true,
        "armed": true
    },
    {
        "name": "Ingerimmshammer",
        "combattech": "Impact Weapons",
        "primeattr": "STR",
        "threshold": 14,
        "damage": "1W6",
        "bonus": 3,
        "at": 0,
        "pa": -2,
        "range": 2,
        "weight": "0,5Stn",
        "price": 125,
        "sf": 999,
        "primeattrID": "ATTR_8",
        "combattechID": "CT_5",
        "improvised": false,
        "url": "index.php/ingerimmshammer.html",
        "clsrng": true,
        "armed": true,
        "templateID": "ITEMTPL_512"
    },
    {
        "name": "Oger-Keule",
        "combattech": "Impact Weapons",
        "primeattr": "STR",
        "threshold": 22,
        "damage": "2W6",
        "bonus": 7,
        "at": 0,
        "pa": 0,
        "range": 3,
        "weight": "6Stn",
        "price": 10,
        "sf": 999,
        "primeattrID": "ATTR_8",
        "combattechID": "CT_5",
        "improvised": false,
        "url": "index.php/oger-keule.html",
        "clsrng": true,
        "armed": true
    },
    {
        "name": "Koscher Grevenstecken",
        "combattech": "Impact Weapons",
        "primeattr": "STR",
        "threshold": 16,
        "damage": "1W3",
        "bonus": 1,
        "at": -1,
        "pa": -2,
        "range": 2,
        "weight": "1,5Stn",
        "price": 18,
        "sf": 999,
        "primeattrID": "ATTR_8",
        "combattechID": "CT_5",
        "improvised": true,
        "url": "index.php/holzhammer-i.html",
        "clsrng": true,
        "armed": true
    },
    {
        "name": "Schmiedewerkzeug",
        "combattech": "Impact Weapons",
        "primeattr": "STR",
        "threshold": 14,
        "damage": "1W6",
        "bonus": 3,
        "at": -1,
        "pa": -2,
        "range": 2,
        "weight": "1,5Stn",
        "price": 999,
        "sf": 999,
        "primeattrID": "ATTR_8",
        "combattechID": "CT_5",
        "improvised": true,
        "url": "index.php/schmiedewerkzeug-i.html",
        "clsrng": true,
        "armed": true
    },
    {
        "name": "Shillelagh (Wurzelholzkeule)",
        "combattech": "Impact Weapons",
        "primeattr": "STR",
        "threshold": 13,
        "damage": "1W6",
        "bonus": 2,
        "at": 0,
        "pa": -2,
        "range": 2,
        "weight": "1Stn",
        "price": 5,
        "sf": 999,
        "primeattrID": "ATTR_8",
        "combattechID": "CT_5",
        "improvised": false,
        "url": "index.php/shillelagh-wurzelholzkeule.html",
        "clsrng": true,
        "armed": true,
        "templateID": "ITEMTPL_526"
    },
    {
        "name": "Steinbeil",
        "combattech": "Impact Weapons",
        "primeattr": "STR",
        "threshold": 14,
        "damage": "1W6",
        "bonus": 1,
        "at": -1,
        "pa": -2,
        "range": 2,
        "weight": "0,5Stn",
        "price": 4,
        "sf": 999,
        "primeattrID": "ATTR_8",
        "combattechID": "CT_5",
        "improvised": false,
        "url": "index.php/steinbeil.html",
        "clsrng": true,
        "armed": true
    },
    {
        "name": "Steinhammer",
        "combattech": "Impact Weapons",
        "primeattr": "STR",
        "threshold": 14,
        "damage": "1W6",
        "bonus": 2,
        "at": 0,
        "pa": -3,
        "range": 2,
        "weight": "1Stn",
        "price": 20,
        "sf": 999,
        "primeattrID": "ATTR_8",
        "combattechID": "CT_5",
        "improvised": false,
        "url": "index.php/steinhammer.html",
        "clsrng": true,
        "armed": true
    },
    {
        "name": "Torfgabel",
        "combattech": "Impact Weapons",
        "primeattr": "STR",
        "threshold": 15,
        "damage": "1W6",
        "bonus": 3,
        "at": -1,
        "pa": -3,
        "range": 2,
        "weight": "1Stn",
        "price": 25,
        "sf": 999,
        "primeattrID": "ATTR_8",
        "combattechID": "CT_5",
        "improvised": false,
        "url": "index.php/torfgabel.html",
        "clsrng": true,
        "armed": true,
        "templateID": "ITEMTPL_542"
    },
    {
        "name": "Yeti-Keule",
        "combattech": "Impact Weapons",
        "primeattr": "STR",
        "threshold": 18,
        "damage": "2W6",
        "bonus": 7,
        "at": 0,
        "pa": 0,
        "range": 3,
        "weight": "5,5Stn",
        "price": 9,
        "sf": 999,
        "primeattrID": "ATTR_8",
        "combattechID": "CT_5",
        "improvised": false,
        "url": "index.php/yeti-keule.html",
        "clsrng": true,
        "armed": true
    }
]